parker/__init__.py
parker/client.py
parker/configloader.py
parker/consumemodel.py
parker/consumepage.py
parker/consumestore.py
parker/crawlmodel.py
parker/crawlpage.py
parker/fileops.py
parker/mediafile.py
parker/page.py
parker/parsedpage.py
parker/parser.py
parker/queues.py
parker/redisset.py
parker/store.py
parker/stringops.py
parker/workers.py
parker/config/client.json
parker/config/parker.json
parker/config/redis.json
parker/config/sites/staples.json
Parker-0.9.6.data/scripts/parker-clean
Parker-0.9.6.data/scripts/parker-config
Parker-0.9.6.data/scripts/parker-crawl
Parker-0.9.6.dist-info/DESCRIPTION.rst
Parker-0.9.6.dist-info/METADATA
Parker-0.9.6.dist-info/metadata.json
Parker-0.9.6.dist-info/RECORD
Parker-0.9.6.dist-info/top_level.txt
Parker-0.9.6.dist-info/WHEEL
