Metadata-Version: 1.0
Name: Parker
Version: 0.9.6
Summary: A web spider for collecting specific data across a set of configured sites
Home-page: http://github.com/nefarioustim/parker/
Author: Tim Huegdon
Author-email: tim@nefariousdesigns.co.uk
License: GPL v3
Platform: UNKNOWN
